setup.py
ychartspy/__init__.py
ychartspy/client.py
ychartspy/constants.py
ychartspy.egg-info/PKG-INFO
ychartspy.egg-info/SOURCES.txt
ychartspy.egg-info/dependency_links.txt
ychartspy.egg-info/requires.txt
ychartspy.egg-info/top_level.txt
ychartspy/tests/__init__.py
ychartspy/tests/test_client.py