Metadata-Version: 1.0
Name: ychartspy
Version: 0.1.1
Summary: Python Client for YCharts
Home-page: UNKNOWN
Author: Gregory Rehm
Author-email: UNKNOWN
License: UNKNOWN
Platform: UNKNOWN
